stay/__init__.py
stay/stay.py
stay-0.1.10.post7.dist-info/LICENSE
stay-0.1.10.post7.dist-info/METADATA
stay-0.1.10.post7.dist-info/WHEEL
stay-0.1.10.post7.dist-info/top_level.txt
stay-0.1.10.post7.dist-info/RECORD
