Metadata-Version: 2.1
Name: stay
Version: 0.1.10.post7
Summary: Simple, even Trivial Alternative to Yaml
Home-page: https://github.com/amogorkon/stay
Author: Anselm Kiefner
Author-email: stay-pypi@anselm.kiefner.de
License: MIT
Keywords: json,yaml,toml,config,simple,alternative
Platform: UNKNOWN
Classifier: Development Status :: 4 - Beta
Classifier: Intended Audience :: Developers
Classifier: Natural Language :: English
Classifier: License :: OSI Approved :: MIT License
Classifier: Operating System :: OS Independent
Classifier: Programming Language :: Python :: 3 :: Only
Classifier: Programming Language :: Python :: Implementation :: CPython
Classifier: Topic :: Text Processing :: Markup
Requires-Python: >3.5
